LICENSE
zeroed/__init__.py
zeroed/cli.py
zeroed/zeroed.py
zeroed-0.1.0rc1.dist-info/entry_points.txt
zeroed-0.1.0rc1.dist-info/LICENSE
zeroed-0.1.0rc1.dist-info/WHEEL
zeroed-0.1.0rc1.dist-info/METADATA
zeroed-0.1.0rc1.dist-info/RECORD
