Metadata-Version: 2.1
Name: zeroed
Version: 0.1.0rc1
Summary: Zeroed is a CLI package for resetting trash and apps to the settings of certain apps on Linux.
Home-page: https://github.com/snakypy/zeroed
License: MIT
Keywords: zeroed,reset
Author: William C. Canin
Author-email: william.costa.canin@gmail.com
Requires-Python: >=3.8,<4.0
Classifier: Intended Audience :: Developers
Classifier: License :: OSI Approved :: MIT License
Classifier: Operating System :: POSIX
Classifier: Programming Language :: Python :: 3
Classifier: Programming Language :: Python :: 3.8
Requires-Dist: click (>=7.1.1,<8.0.0)
Requires-Dist: docopt (>=0.6.2,<0.7.0)
Project-URL: Bug Tracker, https://github.com/snakypy/zeroed/issues
Project-URL: Repository, https://github.com/snakypy/zeroed
